DeepSomaticCopy/RLCNA.py
DeepSomaticCopy/__init__.py
DeepSomaticCopy/pipeline.py
DeepSomaticCopy/process.py
DeepSomaticCopy/runBAM.py
DeepSomaticCopy/scaler.py
DeepSomaticCopy/shared.py
deepsomaticcopy-0.0.26.dist-info/METADATA
deepsomaticcopy-0.0.26.dist-info/WHEEL
deepsomaticcopy-0.0.26.dist-info/entry_points.txt
deepsomaticcopy-0.0.26.dist-info/licenses/LICENSE
deepsomaticcopy-0.0.26.dist-info/RECORD
